[
  {
    "step": 1,
    "time": "08:00",
    "agent_id": "ceo",
    "agent_name": "CEO（创始人的每日工作）",
    "action": "派发任务给产品负责人",
    "output": "已派发任务给产品负责人：优化注册流程，提升转化率",
    "timestamp": "2026-02-26T23:04:16.930328"
  },
  {
    "step": 2,
    "time": "09:00",
    "agent_id": "product-lead",
    "agent_name": "产品负责人",
    "action": "分析需求，制定方案",
    "output": "需求分析完成：简化注册流程从 5 步到 3 步，预期提升转化率 10%",
    "timestamp": "2026-02-26T23:04:17.431073"
  },
  {
    "step": 3,
    "time": "09:30",
    "agent_id": "user-researcher",
    "agent_name": "用户研究员",
    "action": "用户研究，验证需求",
    "output": "用户研究完成：50% 用户反馈注册流程太复杂，建议简化",
    "timestamp": "2026-02-26T23:04:17.931561"
  },
  {
    "step": 4,
    "time": "10:00",
    "agent_id": "ux-designer",
    "agent_name": "UX设计师",
    "action": "设计交互原型",
    "output": "交互原型完成：新注册流程设计，符合用户习惯",
    "timestamp": "2026-02-26T23:04:18.431831"
  },
  {
    "step": 5,
    "time": "11:00",
    "agent_id": "fullstack-dev",
    "agent_name": "全栈工程师",
    "action": "功能开发实现",
    "output": "开发完成：前端 + 后端实现，单元测试通过",
    "timestamp": "2026-02-26T23:04:18.932154"
  },
  {
    "step": 6,
    "time": "14:00",
    "agent_id": "qa-automation",
    "agent_name": "QA自动化工程师",
    "action": "自动化测试",
    "output": "测试完成：功能测试 + 性能测试通过，无阻塞问题",
    "timestamp": "2026-02-26T23:04:19.432342"
  },
  {
    "step": 7,
    "time": "15:00",
    "agent_id": "devops-engineer",
    "agent_name": "DevOps工程师",
    "action": "部署上线",
    "output": "部署完成：灰度发布 10% 流量，监控正常",
    "timestamp": "2026-02-26T23:04:19.932657"
  },
  {
    "step": 8,
    "time": "16:00",
    "agent_id": "technical-writer",
    "agent_name": "技术文档专家",
    "action": "更新文档",
    "output": "文档更新完成：API 文档 + 用户手册已发布",
    "timestamp": "2026-02-26T23:04:20.433022"
  },
  {
    "step": 9,
    "time": "17:00",
    "agent_id": "content-strategist",
    "agent_name": "内容策略师",
    "action": "发布更新公告",
    "output": "公告发布完成：已推送给所有用户，阅读率 60%",
    "timestamp": "2026-02-26T23:04:20.933463"
  }
]